africamonitor.py
africamonitor-0.1.4.dist-info/LICENSE.txt
africamonitor-0.1.4.dist-info/METADATA
africamonitor-0.1.4.dist-info/WHEEL
africamonitor-0.1.4.dist-info/top_level.txt
africamonitor-0.1.4.dist-info/RECORD
