Metadata-Version: 2.1
Name: africamonitor
Version: 0.1.4
Summary: An API providing access to a relational database with macroeconomic data for Africa.
Home-page: https://africamonitor.ifw-kiel.de/
Author: Sebastian Krantz
Author-email: sebastian.krantz@graduateinstitute.ch
License: GPL-3
Project-URL: Bug Reports, https://github.com/IFW-Macro-Research-Group/africamonitor
Keywords: africa,macroeconomic,data,API
Classifier: Development Status :: 5 - Production/Stable
Classifier: License :: OSI Approved :: GNU General Public License v3 (GPLv3)
Classifier: Programming Language :: Python :: 3
Requires-Python: >=3.1
License-File: LICENSE.txt
Requires-Dist: connectorx
Requires-Dist: pyarrow
Requires-Dist: polars
